LICENSE
README.md
pyproject.toml
setup.py
SmartParams.egg-info/PKG-INFO
SmartParams.egg-info/SOURCES.txt
SmartParams.egg-info/dependency_links.txt
SmartParams.egg-info/requires.txt
SmartParams.egg-info/top_level.txt
smartparams/__init__.py
smartparams/register.py
smartparams/smart.py
smartparams/io/__init__.py
smartparams/io/json.py
smartparams/io/yaml.py
smartparams/resolvers/__init__.py
smartparams/resolvers/missing.py
smartparams/types/__init__.py
smartparams/types/builtins/__init__.py
smartparams/types/builtins/bool.py
smartparams/types/builtins/dict.py
smartparams/types/builtins/float.py
smartparams/types/builtins/int.py
smartparams/types/builtins/list.py
smartparams/types/builtins/none.py
smartparams/types/builtins/set.py
smartparams/types/builtins/str.py
smartparams/types/builtins/tuple.py
smartparams/types/pathlib/__init__.py
smartparams/types/pathlib/path.py
smartparams/types/smartparams/__init__.py
smartparams/types/smartparams/smart.py
smartparams/types/typing/__init__.py
smartparams/types/typing/any.py
smartparams/types/typing/callable.py
smartparams/types/typing/forwardref.py
smartparams/types/typing/type.py
smartparams/utils/__init__.py
smartparams/utils/default.py
smartparams/utils/directory.py
smartparams/utils/imports.py
smartparams/utils/loggers.py
smartparams/utils/parser.py
smartparams/utils/typing.py
smartparams/utils/vocab.py
tests/__init__.py
tests/commons/__init__.py
tests/commons/classes.py
tests/integration/__init__.py
tests/integration/test_smart.py
tests/integration/io/__init__.py
tests/integration/io/test_json.py
tests/integration/io/test_yaml.py
tests/unit/__init__.py
tests/unit/test_register.py
tests/unit/test_smart.py
tests/unit/resolvers/__init__.py
tests/unit/resolvers/test_missing.py
tests/unit/types/__init__.py
tests/unit/types/builtins/__init__.py
tests/unit/types/builtins/test_bool.py
tests/unit/types/builtins/test_dict.py
tests/unit/types/builtins/test_float.py
tests/unit/types/builtins/test_int.py
tests/unit/types/builtins/test_list.py
tests/unit/types/builtins/test_none.py
tests/unit/types/builtins/test_set.py
tests/unit/types/builtins/test_str.py
tests/unit/types/builtins/test_tuple.py
