Metadata-Version: 2.1
Name: SmartParams
Version: 1.0.0
Summary: The tool for advanced project configuration with python object injection.
Home-page: https://gitlab.com/mateusz.baran/smartparams
Author: Mateusz Baran
Author-email: mateusz.baran.sanok@gmail.com
Maintainer: Mateusz Baran
Maintainer-email: mateusz.baran.sanok@gmail.com
License: MIT
Classifier: Development Status :: 4 - Beta
Classifier: Programming Language :: Python
Classifier: Programming Language :: Python :: 3
Classifier: Programming Language :: Python :: 3 :: Only
Classifier: Programming Language :: Python :: 3.10
Classifier: Operating System :: OS Independent
Classifier: License :: OSI Approved :: MIT License
Requires-Python: >=3.10, <4
Provides-Extra: dev
License-File: LICENSE
